build/lib/picture/Picture.py
picture/Picture.py
pictureda-1.0.1.dist-info/METADATA
pictureda-1.0.1.dist-info/WHEEL
pictureda-1.0.1.dist-info/top_level.txt
pictureda-1.0.1.dist-info/RECORD
