Metadata-Version: 2.1
Name: pictureda
Version: 1.0.1
Summary: picture
Author: Dada.cod
Author-email: 626987961@qq.com
License: MIT
Keywords: picture
